{
  "slug": "alkali-flat-hot-spring-nv",
  "name": "Alkali Flat Hot Spring",
  "lat": 37.825505,
  "lng": -117.338233,
  "state": "Nevada",
  "state_slug": "nevada",
  "state_code": "NV",
  "city": "Esmeralda County",
  "city_slug": "esmeralda-county",
  "county": "Esmeralda",
  "county_slug": "esmeralda",
  "geocoded_city": "Esmeralda County Area",
  "sources": {
    "rockhounding_org": {
      "found": false,
      "url": "https://rockhounding.org/gem-and-mineral-hunting/rockhounding-in-nevada.html"
    },
    "mindat": {
      "found": false,
      "url": "https://www.mindat.org/search.php?q=Alkali%20Flat%20Hot%20Spring%20Nevada"
    },
    "blm": {
      "found": true,
      "url": "https://www.blm.gov/programs/recreation/permits-and-fees",
      "land_type_hint": "public_blm",
      "description_snippet": "Nevada BLM land — typical rules: personal use only, no permit required for recreational collecting, 25 lb/day limit per FLPMA."
    },
    "rockhounding_map": {
      "found": false,
      "url": "https://rockhoundingmap.com/?s=Alkali%20Flat%20Hot%20Spring",
      "description_snippet": null
    },
    "alltrails": {
      "found": false,
      "url": "https://www.alltrails.com/search?q=Alkali%20Flat%20Hot%20Spring%20Nevada"
    },
    "web_search": {
      "found": false
    }
  },
  "merged": {
    "description_snippets": [
      "[blm] Nevada BLM land — typical rules: personal use only, no permit required for recreational collecting, 25 lb/day limit per FLPMA."
    ],
    "images_found": [],
    "land_type": "public_blm",
    "scrape_quality": "partial",
    "sources_found": 1
  },
  "terrain": {
    "elevation": {
      "feet": 4997,
      "meters": 1523
    },
    "slope": "gentle slope",
    "nearest_city": null,
    "roads": null,
    "water_features": null,
    "protected_areas": null,
    "analyzed_at": "2026-04-21T19:41:15.239Z"
  },
  "scraped_at": "2026-04-21T19:41:15.239Z",
  "scrape_quality": "partial"
}