{
  "slug": "caldwell-nc",
  "name": "Caldwell",
  "lat": 35.465529,
  "lng": -80.826959,
  "state": "North Carolina",
  "state_slug": "north-carolina",
  "state_code": "NC",
  "city": "Cornelius",
  "city_slug": "cornelius",
  "county": "Mecklenburg",
  "county_slug": "mecklenburg",
  "geocoded_city": "Cornelius",
  "sources": {
    "rockhounding_org": {
      "found": false,
      "url": "https://rockhounding.org/gem-and-mineral-hunting/rockhounding-in-north-carolina.html"
    },
    "mindat": {
      "found": false,
      "url": "https://www.mindat.org/search.php?q=Caldwell%20North%20Carolina"
    },
    "blm": {
      "found": false
    },
    "rockhounding_map": {
      "found": false,
      "url": "https://rockhoundingmap.com/?s=Caldwell"
    },
    "alltrails": {
      "found": false,
      "url": "https://www.alltrails.com/search?q=Caldwell%20North%20Carolina"
    },
    "web_search": {
      "found": false
    }
  },
  "merged": {
    "description_snippets": [],
    "images_found": [],
    "land_type": null,
    "scrape_quality": "minimal",
    "sources_found": 0
  },
  "terrain": {
    "elevation": null,
    "slope": null,
    "nearest_city": null,
    "roads": null,
    "water_features": null,
    "protected_areas": null,
    "analyzed_at": "2026-04-22T02:30:39.169Z"
  },
  "scraped_at": "2026-04-22T02:30:39.169Z",
  "scrape_quality": "minimal"
}