{
  "slug": "fogelsanger-quarry-ny",
  "name": "Fogelsanger Quarry",
  "lat": 42.899758,
  "lng": -78.740661,
  "state": "New York",
  "state_slug": "new-york",
  "state_code": "NY",
  "city": "Town of Cheektowaga",
  "city_slug": "town-of-cheektowaga",
  "county": "Erie",
  "county_slug": "erie",
  "geocoded_city": "Town of Cheektowaga",
  "sources": {
    "rockhounding_org": {
      "found": false,
      "url": "https://rockhounding.org/gem-and-mineral-hunting/rockhounding-in-new-york.html"
    },
    "mindat": {
      "found": false,
      "url": "https://www.mindat.org/search.php?q=Fogelsanger%20Quarry%20New%20York"
    },
    "blm": {
      "found": false
    },
    "rockhounding_map": {
      "found": false,
      "url": "https://rockhoundingmap.com/?s=Fogelsanger%20Quarry",
      "description_snippet": null
    },
    "alltrails": {
      "found": false,
      "url": "https://www.alltrails.com/search?q=Fogelsanger%20Quarry%20New%20York"
    },
    "web_search": {
      "found": false
    }
  },
  "merged": {
    "description_snippets": [],
    "images_found": [],
    "land_type": null,
    "scrape_quality": "minimal",
    "sources_found": 0
  },
  "terrain": {
    "elevation": null,
    "slope": "flat",
    "nearest_city": null,
    "roads": null,
    "water_features": null,
    "protected_areas": null,
    "analyzed_at": "2026-04-21T18:46:23.607Z"
  },
  "scraped_at": "2026-04-21T18:46:23.608Z",
  "scrape_quality": "minimal"
}