{
  "slug": "matahuska-river-ak",
  "name": "Matahuska River",
  "lat": 61.783337,
  "lng": -148.453701,
  "state": "Alaska",
  "state_slug": "alaska",
  "state_code": "AK",
  "city": "Matanuska-Susitna Borough",
  "city_slug": "matanuska-susitna-borough",
  "county": "Matanuska-Susitna Borough",
  "county_slug": "matanuska-susitna-borough",
  "geocoded_city": "Matanuska-Susitna Borough",
  "sources": {
    "rockhounding_org": {
      "found": false,
      "url": "https://rockhounding.org/gem-and-mineral-hunting/rockhounding-in-alaska.html"
    },
    "mindat": {
      "found": false,
      "url": "https://www.mindat.org/search.php?q=Matahuska%20River%20Alaska"
    },
    "blm": {
      "found": false
    },
    "rockhounding_map": {
      "found": false,
      "url": "https://rockhoundingmap.com/?s=Matahuska%20River",
      "description_snippet": null
    },
    "alltrails": {
      "found": false,
      "url": "https://www.alltrails.com/search?q=Matahuska%20River%20Alaska"
    },
    "web_search": {
      "found": false
    }
  },
  "merged": {
    "description_snippets": [],
    "images_found": [],
    "land_type": null,
    "scrape_quality": "minimal",
    "sources_found": 0
  },
  "terrain": {
    "elevation": {
      "feet": 810,
      "meters": 247
    },
    "slope": null,
    "nearest_city": null,
    "roads": null,
    "water_features": null,
    "protected_areas": null,
    "analyzed_at": "2026-04-21T18:27:21.463Z"
  },
  "scraped_at": "2026-04-21T18:27:21.464Z",
  "scrape_quality": "minimal"
}